topsisSortLib/__init__.py
topsisSortLib/topsis_Sort_B.py
topsisSortLib-1.0.0.dist-info/LICENSE
topsisSortLib-1.0.0.dist-info/METADATA
topsisSortLib-1.0.0.dist-info/WHEEL
topsisSortLib-1.0.0.dist-info/top_level.txt
topsisSortLib-1.0.0.dist-info/RECORD
