Metadata-Version: 2.1
Name: topsisSortLib
Version: 1.0.0
Summary: Topsis-Sort-B
Author: gilbertomoj
Author-email: gibamedeirosgc@gmail.com
Keywords: python,topsis,topsis-sort-b
Classifier: Development Status :: 3 - Alpha
Classifier: Intended Audience :: Education
Classifier: Programming Language :: Python :: 2
Classifier: Programming Language :: Python :: 3
Classifier: Operating System :: MacOS :: MacOS X
Classifier: Operating System :: Microsoft :: Windows
License-File: LICENSE
Requires-Dist: numpy
